sombra-0.3.5.dist-info/METADATA
sombra-0.3.5.dist-info/WHEEL
sombra-0.3.5.dist-info/entry_points.txt
sombra/__init__.py
sombra/__init__.pyi
sombra/__pycache__/__init__.cpython-312.pyc
sombra/_cli.py
sombra/sombra.cpython-313-x86_64-linux-gnu.so
sombra-0.3.5.dist-info/RECORD
