Metadata-Version: 2.4
Name: sombra
Version: 0.3.5
Classifier: Development Status :: 4 - Beta
Classifier: Intended Audience :: Developers
Classifier: License :: OSI Approved :: MIT License
Classifier: Programming Language :: Python :: 3
Classifier: Programming Language :: Python :: 3.11
Classifier: Programming Language :: Python :: 3.12
Classifier: Programming Language :: Python :: 3.13
Classifier: Programming Language :: Rust
Classifier: Topic :: Database
Classifier: Topic :: Software Development :: Libraries
Summary: A high-performance graph database with ACID transactions
Keywords: graph,database,graphdb,acid,transactions,rust,performance
Author-email: mask <maskdotdev@gmail.com>
License: MIT
Requires-Python: >=3.11
Project-URL: Homepage, https://github.com/maskdotdev/sombra
Project-URL: Repository, https://github.com/maskdotdev/sombra
Project-URL: Issues, https://github.com/maskdotdev/sombra/issues
